nlp_profiler/__init__.py
nlp_profiler/constants.py
nlp_profiler/core.py
nlp_profiler/generate_features/__init__.py
nlp_profiler/generate_features/parallelisation_methods/__init__.py
nlp_profiler/granular_features/__init__.py
nlp_profiler/granular_features/alphanumeric.py
nlp_profiler/granular_features/chars_and_spaces.py
nlp_profiler/granular_features/dates.py
nlp_profiler/granular_features/duplicates.py
nlp_profiler/granular_features/emojis.py
nlp_profiler/granular_features/non_alphanumeric.py
nlp_profiler/granular_features/noun_phase_count.py
nlp_profiler/granular_features/numbers.py
nlp_profiler/granular_features/punctuations.py
nlp_profiler/granular_features/sentences.py
nlp_profiler/granular_features/stop_words.py
nlp_profiler/granular_features/words.py
nlp_profiler/high_level_features/__init__.py
nlp_profiler/high_level_features/ease_of_reading_check.py
nlp_profiler/high_level_features/grammar_quality_check.py
nlp_profiler/high_level_features/sentiment_polarity.py
nlp_profiler/high_level_features/sentiment_subjectivity.py
nlp_profiler/high_level_features/spelling_quality_check.py
nlp_profiler-0.0.3.dist-info/METADATA
nlp_profiler-0.0.3.dist-info/RECORD
nlp_profiler-0.0.3.dist-info/WHEEL
nlp_profiler-0.0.3.dist-info/top_level.txt
slow-tests/__init__.py
slow-tests/acceptance_tests/__init__.py
slow-tests/acceptance_tests/test_apply_text_profiling.py
slow-tests/acceptance_tests/data/expected_profiled_dataframe_ease_of_reading_check.csv
slow-tests/acceptance_tests/data/expected_profiled_dataframe_grammar_check.csv
slow-tests/performance_tests/__init__.py
slow-tests/performance_tests/common_functions.py
slow-tests/performance_tests/test_perf_ease_of_reading_check.py
slow-tests/performance_tests/test_perf_grammar_check.py
slow-tests/performance_tests/test_perf_noun_phase.py
slow-tests/performance_tests/test_perf_spelling_check.py
tests/__init__.py
tests/acceptance_tests/__init__.py
tests/acceptance_tests/test_apply_text_profiling.py
tests/acceptance_tests/data/expected_profiled_dataframe.csv
tests/acceptance_tests/data/expected_profiled_dataframe_no_granular.csv
