Metadata-Version: 2.1
Name: nlp-profiler
Version: 0.0.3
Summary: A simple NLP library allows profiling datasets with one or more text columns.
Home-page: https://github.com/neomatrix369/nlp_profiler
Author: Mani Sarkar
License: Apache 2.0
Download-URL: https://github.com/neomatrix369/nlp_profiler/releases/tag/v0.0.3
Keywords: nlp profiler nlpprofiler nlp_profiler nlp-profiler nlpprof profile profiling
Platform: UNKNOWN
Classifier: Development Status :: 2 - Pre-Alpha
Classifier: Topic :: Software Development :: Build Tools
Classifier: Topic :: Scientific/Engineering :: Artificial Intelligence
Classifier: Topic :: Text Processing
Classifier: Topic :: Text Processing :: General
Classifier: Topic :: Utilities
Classifier: Operating System :: OS Independent
Classifier: Intended Audience :: Developers
Classifier: License :: OSI Approved :: Apache Software License
Classifier: Natural Language :: English
Classifier: Programming Language :: Python :: 3
Classifier: Programming Language :: Python :: 3.6
Classifier: Programming Language :: Python :: 3.7
Classifier: Programming Language :: Python :: 3.8
Requires-Python: >=3.6.0
Requires-Dist: textblob (>=0.15.3)
Requires-Dist: nltk (>=3.5)
Requires-Dist: language-tool-python (>=2.3.1)
Requires-Dist: requests (>=2.23.0)
Requires-Dist: emoji (>=0.5.4)
Requires-Dist: tqdm (==4.46.0)
Requires-Dist: joblib (>=0.14.1)
Requires-Dist: ipython (>=7.12.0)
Requires-Dist: spacy (<3.0.0,>=2.3.0)
Requires-Dist: pandas
Requires-Dist: swifter (>=1.0.3)
Requires-Dist: en-core-web-sm
Requires-Dist: textstat (>=0.7.0)
